pymablock/__init__.py
pymablock/_version.py
pymablock/algorithm_parsing.py
pymablock/algorithms.py
pymablock/block_diagonalization.py
pymablock/kpm.py
pymablock/linalg.py
pymablock/number_ordered_form.py
pymablock/second_quantization.py
pymablock/series.py
pymablock/tests/__init__.py
pymablock/tests/test_block_diagonalization.py
pymablock/tests/test_kpm.py
pymablock/tests/test_linalg.py
pymablock/tests/test_number_ordered_form.py
pymablock/tests/test_second_quantization.py
pymablock/tests/test_series.py
pymablock/tests/test_block_diagonalization/test_number_products_one_block.yml
pymablock/tests/test_block_diagonalization/test_number_products_three_block.yml
pymablock/tests/test_block_diagonalization/test_number_products_two_block.yml
pymablock-2.2.0.dist-info/METADATA
pymablock-2.2.0.dist-info/WHEEL
pymablock-2.2.0.dist-info/licenses/AUTHORS.md
pymablock-2.2.0.dist-info/licenses/LICENSE
pymablock-2.2.0.dist-info/RECORD
