Metadata-Version: 2.4
Name: pymablock
Version: 2.2.0
Summary: Numerical and symbolic implementation of quasi-degenerate perturbation theory
Project-URL: Documentation, https://pymablock.readthedocs.io/en/latest/
Project-URL: Repository, https://gitlab.kwant-project.org/qt/pymablock
Project-URL: Bug Tracker, https://gitlab.kwant-project.org/qt/pymablock/-/issues
Author: Pymablock developers
License-File: AUTHORS.md
License-File: LICENSE
Classifier: Development Status :: 5 - Production/Stable
Classifier: Intended Audience :: Science/Research
Classifier: License :: OSI Approved :: BSD License
Classifier: Programming Language :: Python :: 3.11
Classifier: Programming Language :: Python :: 3.12
Classifier: Programming Language :: Python :: 3.13
Classifier: Topic :: Scientific/Engineering :: Physics
Requires-Python: >=3.11
Requires-Dist: numpy>=1.26
Requires-Dist: packaging>=22.0
Requires-Dist: python-mumps<0.1,>=0.0.1
Requires-Dist: scipy>=1.12
Requires-Dist: sympy>=1.13
Provides-Extra: docs
Requires-Dist: sphinx-book-theme>=1.1.0; extra == 'docs'
Requires-Dist: sphinx-tippy; extra == 'docs'
Provides-Extra: test
Requires-Dist: pytest; extra == 'test'
Requires-Dist: pytest-cov; extra == 'test'
Requires-Dist: pytest-randomly; extra == 'test'
Requires-Dist: pytest-regressions; extra == 'test'
